praisonaiagent/__init__.py
praisonaiagent-0.0.1.dist-info/METADATA
praisonaiagent-0.0.1.dist-info/WHEEL
praisonaiagent-0.0.1.dist-info/RECORD
