Metadata-Version: 2.4
Name: praisonaiagent
Version: 0.0.1
Summary: Intelligent AI Agent Framework for Autonomous Task Execution
Author: MervinPraison
License: MIT
Keywords: agent,ai,automation,autonomous-agent,intelligent-system
Classifier: Development Status :: 4 - Beta
Classifier: License :: OSI Approved :: MIT License
Classifier: Operating System :: OS Independent
Classifier: Programming Language :: Python :: 3
Classifier: Programming Language :: Python :: 3.8
Classifier: Programming Language :: Python :: 3.9
Classifier: Programming Language :: Python :: 3.10
Classifier: Programming Language :: Python :: 3.11
Requires-Python: >=3.8
Requires-Dist: requests>=2.25.1
